<?xml version="1.0" encoding="UTF-8" standalone="no" ?>
<presentation availableOffline="1" guid="EBE028D5-94EC-4137-B142-EC21F24EA9DF" version="0">
	<info>
		<title>2021-08-23 Malola Education Online Exam-38 Level II Mains</title>
		<description/>
	</info>
	<files index="id23" thumbnail="id19" totalSize="4243295">
		<file id="id0">data/apple-touch-icon.png</file>
		<file id="id1">data/browsersupport.js</file>
		<file id="id2">data/favicon.ico</file>
		<file id="id3">data/fonts/fnt0.woff</file>
		<file id="id4">data/fonts/fnt1.woff</file>
		<file id="id5">data/fonts/fnt2.woff</file>
		<file id="id6">data/fonts/fnt3.woff</file>
		<file id="id7">data/fonts/fnt4.woff</file>
		<file id="id8">data/fonts/fnt5.woff</file>
		<file id="id9">data/html5-unsupported.html</file>
		<file id="id10">data/html5.png</file>
		<file id="id11">data/images/img-0490aad2dab3f8edae5786f8e1e92fb4b2c52d91.jpg</file>
		<file id="id12">data/images/img-4d99ca2d3c553aee27ffede1a7a76476a8cc6a8d.jpg</file>
		<file id="id13">data/images/img-7398517b4b1134bf2e5814d09caa98bc6bf174a3.jpg</file>
		<file id="id14">data/images/img-7923f1ffe81a73f5a53207ec75be34b317c52184.PNG</file>
		<file id="id15">data/images/img-819c31cc6549f987b5a73e409b71b5b593b82123.PNG</file>
		<file id="id16">data/images/img-b6a7f23bf9f14534cbf92025b90bee5b1c0f3bfe.jpg</file>
		<file id="id17">data/ismplayer/app_store2x.png</file>
		<file id="id18">data/ismplayer/play.svg</file>
		<file id="id19">data/ismplayer/preview.png</file>
		<file id="id20">data/ismplayer/style.css</file>
		<file id="id21">data/ismplayer/style_mini.css</file>
		<file id="id22">data/player.js</file>
		<file id="id23">index.html</file>
		<file id="id24">ismplayer.html</file>
		<file id="id25">preview.png</file>
	</files>
</presentation>

